aslutils/ASLLexer.py
aslutils/ASLParser.py
aslutils/ASLVisitor.py
aslutils/__init__.py
aslutils/asl2.py
aslutils/asl2c.py
aslutils/asl2py.py
aslutils/asl2vhd.py
aslutils/asl_type.py
aslutils/asl_type_visitor.py
aslutils/asl_value_visitor.py
aslutils/parse_asl_file.py
aslutils-0.1.2.dist-info/LICENSE
aslutils-0.1.2.dist-info/METADATA
aslutils-0.1.2.dist-info/WHEEL
aslutils-0.1.2.dist-info/top_level.txt
aslutils-0.1.2.dist-info/RECORD
