Metadata-Version: 2.1
Name: aslutils
Version: 0.1.2
Summary: Code to parse Arm Specification Language (ASL) files
Home-page: https://github.com/alehed/aslutils.git
Author: Alexander Hedges
Author-email: ahedges@ethz.ch
License: UNKNOWN
Platform: UNKNOWN
Classifier: Development Status :: 3 - Alpha
Classifier: Intended Audience :: Developers
Classifier: Programming Language :: Python :: 3
Classifier: License :: OSI Approved :: MIT License
Classifier: Operating System :: OS Independent
Requires-Python: >=3
Requires-Dist: antlr4-python3-runtime (==4.5.*)
